helloworld.py
helloworld_ashcoder-0.0.1.dist-info/LICENSE.txt
helloworld_ashcoder-0.0.1.dist-info/METADATA
helloworld_ashcoder-0.0.1.dist-info/WHEEL
helloworld_ashcoder-0.0.1.dist-info/top_level.txt
helloworld_ashcoder-0.0.1.dist-info/RECORD
